pylottie/__init__.py
pylottie/lottie.html
pylottie-2024.dist-info/entry_points.txt
pylottie-2024.dist-info/LICENSE.md
pylottie-2024.dist-info/METADATA
pylottie-2024.dist-info/WHEEL
pylottie-2024.dist-info/RECORD
