Metadata-Version: 2.1
Name: pylottie
Version: 2024
Summary: Convert .tgs and .lottie to .webp or .gif using playwright.
Home-page: https://github.com/FHPythonUtils/PyLottie
License: MIT
Author: FredHappyface
Requires-Python: >=3.8,<4.0
Classifier: Development Status :: 5 - Production/Stable
Classifier: Intended Audience :: Developers
Classifier: Intended Audience :: Education
Classifier: License :: OSI Approved :: MIT License
Classifier: Natural Language :: English
Classifier: Operating System :: OS Independent
Classifier: Programming Language :: Python :: 3
Classifier: Programming Language :: Python :: 3.8
Classifier: Programming Language :: Python :: 3.9
Classifier: Programming Language :: Python :: 3.10
Classifier: Programming Language :: Python :: 3.11
Classifier: Programming Language :: Python :: 3.12
Classifier: Programming Language :: Python :: Implementation :: CPython
Classifier: Topic :: Multimedia :: Graphics
Classifier: Topic :: Software Development :: Libraries :: Python Modules
Classifier: Topic :: Utilities
Requires-Dist: Pillow (>=10.2.0,<11)
Requires-Dist: install-playwright (>=0.0.1,<2)
Requires-Dist: playwright (>=1.42.0,<2)
Project-URL: Documentation, https://github.com/FHPythonUtils/PyLottie/blob/master/README.md
Project-URL: Repository, https://github.com/FHPythonUtils/PyLottie
